tshistory_supervision/__init__.py
tshistory_supervision/api.py
tshistory_supervision/cli.py
tshistory_supervision/http.py
tshistory_supervision/migrate.py
tshistory_supervision/schema.py
tshistory_supervision/testutil.py
tshistory_supervision/tsio.py
tshistory_supervision-0.13.1.dist-info/LICENSE
tshistory_supervision-0.13.1.dist-info/METADATA
tshistory_supervision-0.13.1.dist-info/WHEEL
tshistory_supervision-0.13.1.dist-info/entry_points.txt
tshistory_supervision-0.13.1.dist-info/top_level.txt
tshistory_supervision-0.13.1.dist-info/RECORD
